dolarpy/__init__.py
dolarpy/dolarpy.py
dolarpy/exchange.py
dolarpy/settings.py
dolarpy-0.3.1.dist-info/DESCRIPTION.rst
dolarpy-0.3.1.dist-info/METADATA
dolarpy-0.3.1.dist-info/RECORD
dolarpy-0.3.1.dist-info/WHEEL
dolarpy-0.3.1.dist-info/metadata.json
dolarpy-0.3.1.dist-info/top_level.txt
